voc4cat/__init__.py
voc4cat/_version.py
voc4cat/assistant.py
voc4cat/check.py
voc4cat/checks.py
voc4cat/cli.py
voc4cat/config.py
voc4cat/convert.py
voc4cat/convert_043.py
voc4cat/convert_v1.py
voc4cat/convert_v1_helpers.py
voc4cat/docs.py
voc4cat/fields.py
voc4cat/gen_template.py
voc4cat/gh_index.py
voc4cat/merge_vocab.py
voc4cat/models_v1.py
voc4cat/transform.py
voc4cat/utils.py
voc4cat/xlsx_api.py
voc4cat/xlsx_common.py
voc4cat/xlsx_keyvalue.py
voc4cat/xlsx_table.py
voc4cat/profile/readme.md
voc4cat/profile/specification-vocpub-4.7.md
voc4cat/profile/specification-vocpub-5.2.md
voc4cat/profile/vocpub-4.7.ttl
voc4cat/profile/vocpub-5.2.ttl
voc4cat/profile/vp4cat-5.2.ttl
voc4cat/templates/docs/index.html
voc4cat/templates/docs/pylode.css
voc4cat/templates/docs/vocabularies.html
voc4cat/templates/vocab/README.md
voc4cat/templates/vocab/idranges.toml
voc4cat-1.0.1.dist-info/METADATA
voc4cat-1.0.1.dist-info/WHEEL
voc4cat-1.0.1.dist-info/entry_points.txt
voc4cat-1.0.1.dist-info/licenses/LICENSE
voc4cat-1.0.1.dist-info/RECORD
