Metadata-Version: 2.4
Name: voc4cat
Version: 1.0.1
Summary: SKOS vocabulary management tool by NFDI4Cat.
Project-URL: Homepage, https://github.com/nfdi4cat/voc4cat-tool/
Project-URL: Documentation, https://github.com/nfdi4cat/voc4cat-tool/
Project-URL: Changelog, https://github.com/nfdi4cat/voc4cat-tool/blob/main/CHANGELOG.md
Author-email: David Linke <david.linke@catalysis.de>, Peter Philips <peter.philips@surroundaustralia.com>, Nicholas Car <nick@kurrawong.net>, Jamie Feiss <jamie.feiss@surroundaustralia.com>
Maintainer-email: David Linke <david.linke@catalysis.de>
License-Expression: BSD-3-Clause
License-File: LICENSE
Keywords: SKOS,linked data,rdf,spreadsheet,vocabulary,xlsx
Classifier: Development Status :: 5 - Production/Stable
Classifier: Environment :: Console
Classifier: Intended Audience :: Science/Research
Classifier: Operating System :: OS Independent
Classifier: Programming Language :: Python
Classifier: Programming Language :: Python :: 3.10
Classifier: Programming Language :: Python :: 3.11
Classifier: Programming Language :: Python :: 3.12
Classifier: Programming Language :: Python :: 3.13
Classifier: Programming Language :: Python :: 3.14
Requires-Python: >=3.10
Requires-Dist: base32-crockford
Requires-Dist: colorama
Requires-Dist: curies
Requires-Dist: isodate<1.0.0,>=0.7.2; python_version < '3.11'
Requires-Dist: jinja2
Requires-Dist: openpyxl>=3.1.5
Requires-Dist: pillow
Requires-Dist: pydantic>=2.10
Requires-Dist: pyshacl
Requires-Dist: rdflib
Requires-Dist: tomli>=1.1.0; python_version < '3.11'
Provides-Extra: assistant
Requires-Dist: click; extra == 'assistant'
Requires-Dist: levenshtein; extra == 'assistant'
Requires-Dist: sentence-transformers; extra == 'assistant'
Requires-Dist: torch; extra == 'assistant'
Provides-Extra: dev
Requires-Dist: coverage; extra == 'dev'
Requires-Dist: furo; extra == 'dev'
Requires-Dist: mypy; extra == 'dev'
Requires-Dist: myst-parser; extra == 'dev'
Requires-Dist: pytest; extra == 'dev'
Requires-Dist: pytest-subprocess; extra == 'dev'
Requires-Dist: ruff; extra == 'dev'
Requires-Dist: sphinx; extra == 'dev'
Provides-Extra: docs
Requires-Dist: furo; extra == 'docs'
Requires-Dist: myst-parser; extra == 'docs'
Requires-Dist: sphinx; extra == 'docs'
Provides-Extra: lint
Requires-Dist: mypy; extra == 'lint'
Requires-Dist: ruff; extra == 'lint'
Provides-Extra: tests
Requires-Dist: coverage; extra == 'tests'
Requires-Dist: pytest; extra == 'tests'
Requires-Dist: pytest-subprocess; extra == 'tests'
